editables/__init__.py
editables/redirector.py
editables-0.4.dist-info/LICENSE.txt
editables-0.4.dist-info/WHEEL
editables-0.4.dist-info/METADATA
editables-0.4.dist-info/RECORD
